README.rst
setup.cfg
setup.py
Pyppo.egg-info/PKG-INFO
Pyppo.egg-info/SOURCES.txt
Pyppo.egg-info/dependency_links.txt
Pyppo.egg-info/top_level.txt
pyppo/__init__.py
pyppo/exceptions.py
pyppo/pipeline.py
tests/__init__.py
tests/tests.py