Metadata-Version: 1.1
Name: Pyppo
Version: 0.1
Summary: Pyppo is a small flow based programming micro framework
Home-page: https://github.com/madedotcom/pyppo/
Author: made.com
Author-email: dev@made.com
License: UNKNOWN
Keywords: made.com,pipeline,flow,based,functional
Platform: UNKNOWN
Classifier: License :: OSI Approved :: MIT License
Classifier: Programming Language :: Python :: 3.4
Classifier: Programming Language :: Python :: 3.5
Classifier: Topic :: Software Development :: Libraries :: Python Modules
